channels_rabbitmq/__init__.py
channels_rabbitmq/core.py
channels_rabbitmq/multiqueue.py
channels_rabbitmq/reader.py
channels_rabbitmq/util.py
channels_rabbitmq-4.0.0.dist-info/WHEEL
channels_rabbitmq-4.0.0.dist-info/METADATA
channels_rabbitmq-4.0.0.dist-info/RECORD
