Metadata-Version: 2.1
Name: channels-rabbitmq
Version: 4.0.0
Summary: RabbitMQ-based ASGI channel layer implementation
License: BSD
Author: Adam Hooper
Author-email: adam@adamhooper.com
Requires-Python: >=3.8,<4.0
Classifier: License :: Other/Proprietary License
Classifier: Programming Language :: Python :: 3
Classifier: Programming Language :: Python :: 3.8
Classifier: Programming Language :: Python :: 3.9
Requires-Dist: carehare (>=1.0,<2.0)
Requires-Dist: channels (>=3.0,<4.0)
Requires-Dist: msgpack (>=1.0,<2.0)
